xcpy/__init__.py
xcpy/api.py
xcpy-0.2.dist-info/METADATA
xcpy-0.2.dist-info/WHEEL
xcpy-0.2.dist-info/top_level.txt
xcpy-0.2.dist-info/RECORD
