Metadata-Version: 2.1
Name: xcpy
Version: 0.2
Summary: A Python wrapper for the Xeno Canto API
Home-page: https://github.com/NickEvans4130/xcpy
Author: Nick Evans
Author-email: nick.evans4130@gmail.com
Requires-Dist: requests
Requires-Dist: os
